pygluehome/__init__.py
pygluehome/api.py
pygluehome/lock.py
pygluehome-0.1.1.dist-info/LICENSE
pygluehome-0.1.1.dist-info/METADATA
pygluehome-0.1.1.dist-info/WHEEL
pygluehome-0.1.1.dist-info/top_level.txt
pygluehome-0.1.1.dist-info/RECORD
