Metadata-Version: 2.1
Name: pygluehome
Version: 0.1.1
Summary: A library to communicate with Glue Lock
Home-page: https://github.com/magnusnordlander/pygluehome/
Author: Magnus Nordlander
License: UNKNOWN
Project-URL: Bug Tracker, https://github.com/magnusnordlander/pygluehome/issues
Platform: UNKNOWN
Classifier: Programming Language :: Python :: 3
Classifier: License :: OSI Approved :: MIT License
Classifier: Operating System :: OS Independent
Requires-Python: >=3.6
